setup.py
smsapi/__init__.py
smsapi/client.py
smsapi/mime_types.py
smsapi/proxy.py
smsapi/responses.py
smsapi/services.py
smsapi/smil.py
smsapi/actions/__init__.py
smsapi/actions/action.py
smsapi/actions/client.py
smsapi/actions/message.py
smsapi/actions/mms.py
smsapi/actions/phonebook.py
smsapi/actions/sender.py
smsapi/actions/sms.py
smsapi/actions/vms.py
smsapi_pozytywnie.egg-info/PKG-INFO
smsapi_pozytywnie.egg-info/SOURCES.txt
smsapi_pozytywnie.egg-info/dependency_links.txt
smsapi_pozytywnie.egg-info/top_level.txt