Metadata-Version: 1.1
Name: smsapi-pozytywnie
Version: 1.0-beta
Summary: Python library for manage SmsApi account via HTTP/S
Home-page: https://github.com/Kern3l/smsapi-python-client
Author: SMSAPI
Author-email: bok@smsapi.pl
License: Copyright 2013 SMSAPI
